{
  "name": "罗伯特嘉西亚",
  "skills": [
    { "name": "龙跳脚", "type": "投技", "command": "近敌←或→+C" },
    { "name": "首切投", "type": "投技", "command": "近敌←或→+D" },
    { "name": "龙翻蹴", "type": "特殊技", "command": "→+B", "images": ["584_2025031453600245.png"] },
    { "name": "龙击拳", "type": "必杀技", "command": "↓↘→+A或C", "images": ["584_2025031453600454.gif"] },
    { "name": "龙牙", "type": "必杀技", "command": "→↓↘+A或C", "images": ["584_2025031453601936.gif"] },
    { "name": "龙斩翔", "type": "必杀技", "command": "→↓↘+B或D", "images": ["584_2025031453600679.gif"] },
    { "name": "飞燕龙神脚", "type": "必杀技", "command": "空中↓↙←+B或D", "images": ["584_2025031453600502.gif"] },
    { "name": "飞燕旋风脚", "type": "必杀技", "command": "→↘↓↙←+B或D", "images": ["584_2025031453559560.gif"] },
    {
      "name": "极限流连舞脚",
      "type": "必杀技",
      "command": "近敌←↙↓↘→+B或D",
      "description": "打击投，无法防御;最后一击有浮空效果，可追击",
      "images": ["584_2025031453600211.gif"]
    },
    { "name": "霸王翔吼拳", "type": "超必杀技", "command": "→←↙↓↘→+A或C", "images": ["584_2025031453601560.gif"] },
    { "name": "MAX霸王翔吼拳", "type": "超必杀技", "command": "→←↙↓↘→+A或C", "images": ["584_2025031453559539.gif"] },
    { "name": "龙虎乱舞", "type": "超必杀技", "command": "↓↘→↘↓↙←+A或C", "images": ["584_202503145360111.gif"] },
    { "name": "MAX龙虎乱舞", "type": "超必杀技", "command": "↓↘→↘↓↙←+A或C", "images": ["584_2025031453600680.gif"] },
    {
      "name": "无影疾风重段脚",
      "type": "超必杀技",
      "command": "↓↘→↓↘→+B或D",
      "images": ["584_2025031453558913.gif"]
    },
    {
      "name": "MAX无影疾风重段脚",
      "type": "超必杀技",
      "command": "↓↘→↓↘→+B或D",
      "images": ["584_2025031453558506.gif"]
    }
  ]
}
